<?xml version="1.0" encoding="UTF-8"?>
<!DOCTYPE locale SYSTEM "../../../../../lib/pkp/dtd/locale.dtd">

<!--
  * plugins/themes/default-child/locale/en_US/locale.xml
  *
  * Copyright (c) 2014-2016 Simon Fraser University Library
  * Copyright (c) 2003-2016 John Willinsky
  * Distributed under the GNU GPL v2. For full terms see the file docs/COPYING.
  *
  * Localization strings
  -->

<locale name="es_ES" full_name="Español (España)">

	<!--
	QUIZAS DEBA ANADIRSE A LOCALE OJS
	-->
	<message key="plugins.citationLookup.crossref.displayName">Conector de base de datos CrossRef</message>
	<message key="plugins.citationLookup.crossref.description">Conecta la base de datos bibliográfica CrossRef</message>
	<message key="plugins.citationLookup.pubmed.displayName">Connector de base de datos PubMed</message>
	<message key="plugins.citationLookup.pubmed.description">Conecta la base de datos bibliográfica PubMed</message>
	<message key="plugins.citationLookup.worldcat.displayName">Conector de base de datos WorldCat</message>
	<message key="plugins.citationLookup.worldcat.description">Conecta la base de datos bibliográfica WorldCat</message>
	<message key="plugins.citationOutput.vancouver.displayName">Estilo de citado Vancouver</message>
	<message key="plugins.citationOutput.vancouver.description">Implementa el estilo de citado Vancouver</message>
	<message key="plugins.citationOutput.abnt.displayName">Estilo de citado ABNT</message>
	<message key="plugins.citationOutput.abnt.description">Implementa el estilo de citado ABNT</message>
	<message key="plugins.citationOutput.mla.displayName">Estilo de citado MLA</message>
	<message key="plugins.citationOutput.mla.description">Implementa el estilo de citado MLA</message>
	<message key="plugins.citationOutput.apa.displayName">Estilo de citado APA</message>
	<message key="plugins.citationOutput.apa.description">Implementa el estilo de citado APA</message>
	<message key="plugins.citationParser.parscit.displayName">Extractor de citas ParsCit</message>
	<message key="plugins.citationParser.parscit.description">Extrae campos desde un texto plano de citas mediante el servicio ParsCit</message>
	<message key="plugins.citationParser.freecite.displayName">Extractor de citas FreeCite</message>
	<message key="plugins.citationParser.freecite.description">Extrae campos desde un texto plano de citas mediante el servicio FreeCite</message>
	<message key="plugins.citationParser.regex.displayName">Extractor de citas Regular Expressions</message>
	<message key="plugins.citationParser.regex.description">Extrae campos desde un texto plano de citas mediante el servicio regular expressions</message>
	<message key="plugins.citationParser.paracite.displayName">Extractor de citas ParaCite</message>
	<message key="plugins.citationParser.paracite.description">Extrae campos desde un texto plano de citas mediante el servicio ParaCite</message>
	<message key="plugins.generic.recommendByAuthor.displayName">Recomendar Artículos por Autor</message>
	<message key="plugins.generic.recommendByAuthor.description">Este plugin inserta una lista de artículos del mismo autor en la página resumen</message>
	<message key="plugins.generic.recommendByAuthor.heading">Mas artículos del mismo autor</message>
	<message key="plugins.generic.recommendByAuthor.noMetric">Obs.: Este plugin de artículo requiere al menos una estadística/reporte para ser habilitado. Si tu plugin de estadística provee más de una métrica, entonces por favor selecciona una métrica principal en la configuración del administrador y/o en configuración de la revista.</message>
	<message key="plugins.generic.lensGalley.displayName">Visor de artículo eLife Lens</message>
	<message key="plugins.generic.lensGalley.description">Provee soporte de renderizado JATS XML usando eLife Lens.</message>
	<message key="plugins.pubIds.urn.displayName">URN</message><message key="plugins.pubIds.urn.description">This plugin enables the assignment of the Uniform Resource Names to the issues, articles and galleys in OJS.</message><!-- settings form -->
<message key="plugins.pubIds.urn.manager.settings.description">Please configure the URN plug-in to be able to manage and use URNs in OJS:</message><message key="plugins.pubIds.urn.manager.settings.urnObjects">Journal Content</message><message key="plugins.pubIds.urn.manager.settings.urnObjectsRequired">Please choose the objects URNs should be assigned to.</message><message key="plugins.pubIds.urn.manager.settings.explainURNs">Please select the publishing objects that will have Uniform Resource Names (URN) assigned:</message><message key="plugins.pubIds.urn.manager.settings.enableIssueURN">Issues</message><message key="plugins.pubIds.urn.manager.settings.enableSubmissionURN">Articles</message><message key="plugins.pubIds.urn.manager.settings.enableRepresentationURN">Galleys</message><message key="plugins.pubIds.urn.manager.settings.urnPrefix">URN Prefix</message><message key="plugins.pubIds.urn.manager.settings.urnPrefix.description">The URN prefix is the fix, never changing part of the URN (e.g. "urn:nbn:de:0000-").</message><message key="plugins.pubIds.urn.manager.settings.form.urnPrefixPattern">The URN prefix pattern must be in the form "urn:"&lt;NID&gt;":"&lt;NSS&gt;.</message><message key="plugins.pubIds.urn.manager.settings.urnSuffix">URN Suffix</message><message key="plugins.pubIds.urn.manager.settings.urnSuffix.description">A URN suffix can take any form, but must be unique among all publishing objects with the same URN prefix assigned:</message><message key="plugins.pubIds.urn.manager.settings.urnSuffixPattern">Use the pattern entered below to generate URN suffixes. Use %j for journal initials, %v for the volume number, %i for the issue number, %Y for the year, %a for the OJS article ID, %g for the OJS galley ID, %f for the OJS file ID, %p for the page number and %x for "Custom Identifier".</message><message key="plugins.pubIds.urn.manager.settings.urnSuffixPattern.example">For example, vol%viss%ipp%p could create the URN suffix "vol3iss2pp230".</message><message key="plugins.pubIds.urn.manager.settings.urnSuffixPattern.issues">for issues</message><message key="plugins.pubIds.urn.manager.settings.urnSuffixPattern.submissions">for articles</message><message key="plugins.pubIds.urn.manager.settings.urnSuffixPattern.representations">for galleys</message><message key="plugins.pubIds.urn.manager.settings.urnIssueSuffixPatternRequired">Please enter the URN suffix pattern for issues.</message><message key="plugins.pubIds.urn.manager.settings.urnSubmissionSuffixPatternRequired">Please enter the URN suffix pattern for articles.</message><message key="plugins.pubIds.urn.manager.settings.urnRepresentationSuffixPatternRequired">Please enter the URN suffix pattern for galleys.</message><message key="plugins.pubIds.urn.manager.settings.urnSuffixDefault">Use default patterns.</message><message key="plugins.pubIds.urn.manager.settings.urnSuffixDefault.description">%j.v%vi%i for issues<br />%j.v%vi%i.%a for articles<br />%j.v%vi%i.%a.g%g for galleys.</message><message key="plugins.pubIds.urn.manager.settings.urnSuffixCustomIdentifier">Enter an individual URN suffix for each published item. You'll find an additional URN input field on each item's metadata page.</message><message key="plugins.pubIds.urn.manager.settings.checkNo">Check Number</message><message key="plugins.pubIds.urn.manager.settings.checkNo.label">The check number will be automatically calculated and added at the end, as the last digit of an URN.</message><message key="plugins.pubIds.urn.manager.settings.namespace">Namespace</message><message key="plugins.pubIds.urn.manager.settings.namespace.choose">Choose</message><message key="plugins.pubIds.urn.manager.settings.namespace.description">The persistent identifier namespace usually needed for the registration (e.g. at the Deutsche Nationalbibliothek).</message><message key="plugins.pubIds.urn.manager.settings.urnResolver">Resolver URL</message><message key="plugins.pubIds.urn.manager.settings.urnResolver.description">(e.g. http://nbn-resolving.de/)</message><message key="plugins.pubIds.urn.manager.settings.form.urnResolverRequired">Please enter the resolver URL.</message><message key="plugins.pubIds.urn.manager.settings.urnReassign">Reassign URNs</message><message key="plugins.pubIds.urn.manager.settings.urnReassign.description">If you change your URN configuration, URNs that have already been assigned will not be affected. Once the URN configuration is saved, use this button to clear all existing URNs so that the new settings will take effect with existing objects.</message><message key="plugins.pubIds.urn.manager.settings.urnReassign.confirm">Are you sure you wish to delete all existing URNs?</message><!-- metadata form -->
<message key="plugins.pubIds.urn.editor.urn">URN</message><message key="plugins.pubIds.urn.editor.urnObjectTypeIssue">issue</message><message key="plugins.pubIds.urn.editor.urnObjectTypeSubmission">article</message><message key="plugins.pubIds.urn.editor.urnObjectTypeRepresentation">galley</message><message key="plugins.pubIds.urn.editor.customSuffixMissing">The URN cannot be assigned because the custom suffix is missing.</message><message key="plugins.pubIds.urn.editor.patternNotResolved">The URN cannot be assigned because it contains an unresolved pattern.</message><message key="plugins.pubIds.urn.editor.canBeAssigned">What you see is a preview of the URN. Select the checkbox and save the form to assign the URN.</message><message key="plugins.pubIds.urn.editor.assigned">The URN is assigned to this {$pubObjectType}.</message><message key="plugins.pubIds.urn.editor.urnSuffixCustomIdentifierNotUnique">The given URN suffix is already in use for another published item. Please enter a unique URN suffix for each item.</message><message key="plugins.pubIds.urn.editor.clearObjectsURN">Clear URN</message><message key="plugins.pubIds.urn.editor.clearObjectsURN.confirm">Are you sure you wish to delete the existing URN?</message><message key="plugins.pubIds.urn.editor.clearIssueObjectsURN">Clear Issue Objects URNs</message><message key="plugins.pubIds.urn.editor.clearIssueObjectsURN.confirm">Are you sure you wish to delete the existing issue objects URNs?</message><message key="plugins.pubIds.urn.editor.clearIssueObjectsURN.description">Use the following option to clear URNs of all objects (articles and galleys) currently scheduled for this issue.</message><message key="plugins.pubIds.urn.editor.addCheckNo">Add Check Number</message><!-- assignment form -->
<message key="plugins.pubIds.urn.editor.assignURN">Assign the URN {$pubId} to this {$pubObjectType}</message><message key="plugins.pubIds.urn.editor.assignURN.emptySuffix">The URN cannot be assigned because the custom suffix is missing.</message><message key="plugins.pubIds.urn.editor.assignURN.pattern">The URN {$pubId} cannot be assigned because it contains an unresolved pattern.</message><message key="plugins.pubIds.urn.editor.assignURN.assigned">The URN {$pubId} has been assigned.</message><!-- errors -->
<message key="plugins.pubIds.urn.form.checkNoRequired">The check number is missing.</message>
<message key="plugins.pubIds.doi.displayName">DOI</message><message key="plugins.pubIds.doi.description">This plugin enables the assignment of the Digital Object Identifiers to issues, articles and galleys in OJS.</message><message key="plugins.pubIds.doi.readerDisplayName">DOI:</message><!-- settings form -->
<message key="plugins.pubIds.doi.manager.settings.description">Please configure the DOI plug-in to be able to manage and use DOIs in OJS:</message><message key="plugins.pubIds.doi.manager.settings.doiObjects">Journal Content</message><message key="plugins.pubIds.doi.manager.settings.doiObjectsRequired">Please choose the objects DOIs should be assigned to.</message><message key="plugins.pubIds.doi.manager.settings.explainDois">Please select the publishing objects that will have Digital Object Identifiers (DOI) assigned:</message><message key="plugins.pubIds.doi.manager.settings.enableIssueDoi">Issues</message><message key="plugins.pubIds.doi.manager.settings.enableSubmissionDoi">Articles</message><message key="plugins.pubIds.doi.manager.settings.enableRepresentationDoi">Galleys</message><message key="plugins.pubIds.doi.manager.settings.doiPrefix">DOI Prefix</message><message key="plugins.pubIds.doi.manager.settings.doiPrefix.description">The DOI Prefix is assigned by registration agencies (e.g. <a href="http://www.crossref.org" target="_new">CrossRef</a>) and is in the format 10.xxxx (e.g. 10.1234):</message><message key="plugins.pubIds.doi.manager.settings.doiPrefixPattern">The DOI prefix is mandatory and must be in the form 10.xxxx.</message><message key="plugins.pubIds.doi.manager.settings.doiSuffix">DOI Suffix</message><message key="plugins.pubIds.doi.manager.settings.doiSuffix.description">A DOI suffix can take any form, but must be unique among all publishing objects with the same DOI prefix assigned:</message><message key="plugins.pubIds.doi.manager.settings.doiSuffixPattern">Use the pattern entered below to generate DOI suffixes. Use %j for journal initials, %v for the volume number, %i for the issue number, %Y for the year, %a for the OJS article ID, %g for the OJS galley ID, %f for the OJS file ID, %p for the page number and %x for "Custom Identifier".</message><message key="plugins.pubIds.doi.manager.settings.doiSuffixPattern.example">For example, vol%viss%ipp%p could create a DOI such as 10.1234/vol3iss2pp230</message><message key="plugins.pubIds.doi.manager.settings.doiSuffixPattern.issues">for issues</message><message key="plugins.pubIds.doi.manager.settings.doiSuffixPattern.submissions">for articles</message><message key="plugins.pubIds.doi.manager.settings.doiSuffixPattern.representations">for galleys</message><message key="plugins.pubIds.doi.manager.settings.doiSuffixDefault">Use default patterns.</message><message key="plugins.pubIds.doi.manager.settings.doiSuffixDefault.description">%j.v%vi%i for issues<br />%j.v%vi%i.%a for articles<br />%j.v%vi%i.%a.g%g for galleys.</message><message key="plugins.pubIds.doi.manager.settings.doiSuffixCustomIdentifier">Enter an individual DOI suffix for each published item. You'll find an additional DOI input field on each item's meta-data page.</message><message key="plugins.pubIds.doi.manager.settings.doiIssueSuffixPatternRequired">Please enter the DOI suffix pattern for issues.</message><message key="plugins.pubIds.doi.manager.settings.doiSubmissionSuffixPatternRequired">Please enter the DOI suffix pattern for articles.</message><message key="plugins.pubIds.doi.manager.settings.doiRepresentationSuffixPatternRequired">Please enter the DOI suffix pattern for galleys.</message><message key="plugins.pubIds.doi.manager.settings.doiReassign">Reassign DOIs</message><message key="plugins.pubIds.doi.manager.settings.doiReassign.description">If you change your DOI configuration, DOIs that have already been assigned will not be affected. Once the DOI configuration is saved, use this button to clear all existing DOIs so that the new settings will take effect with existing objects.</message><message key="plugins.pubIds.doi.manager.settings.doiReassign.confirm">Are you sure you wish to delete all existing DOIs?</message><!-- metadata form -->
<message key="plugins.pubIds.doi.editor.doi">DOI</message><message key="plugins.pubIds.doi.editor.doiObjectTypeIssue">issue</message><message key="plugins.pubIds.doi.editor.doiObjectTypeSubmission">article</message><message key="plugins.pubIds.doi.editor.doiObjectTypeRepresentation">galley</message><message key="plugins.pubIds.doi.editor.customSuffixMissing">The DOI cannot be assigned because the custom suffix is missing.</message><message key="plugins.pubIds.doi.editor.patternNotResolved">The DOI cannot be assigned because it contains an unresolved pattern.</message><message key="plugins.pubIds.doi.editor.canBeAssigned">What you see is a preview of the DOI. Select the checkbox and save the form to assign the DOI.</message><message key="plugins.pubIds.doi.editor.assigned">The DOI is assigned to this {$pubObjectType}.</message><message key="plugins.pubIds.doi.editor.doiSuffixCustomIdentifierNotUnique">The given DOI suffix is already in use for another published item. Please enter a unique DOI suffix for each item.</message><message key="plugins.pubIds.doi.editor.clearObjectsDoi">Clear DOI</message><message key="plugins.pubIds.doi.editor.clearObjectsDoi.confirm">Are you sure you wish to delete the existing DOI?</message><message key="plugins.pubIds.doi.editor.clearIssueObjectsDoi">Clear Issue Objects DOIs</message><message key="plugins.pubIds.doi.editor.clearIssueObjectsDoi.confirm">Are you sure you wish to delete the existing issue objects DOIs?</message><message key="plugins.pubIds.doi.editor.clearIssueObjectsDoi.description">Use the following option to clear DOIs of all objects (articles and galleys) currently scheduled for this issue.</message><!-- assignment form -->
<message key="plugins.pubIds.doi.editor.assignDoi">Assign the DOI {$pubId} to this {$pubObjectType}</message><message key="plugins.pubIds.doi.editor.assignDoi.emptySuffix">The DOI cannot be assigned because the custom suffix is missing.</message><message key="plugins.pubIds.doi.editor.assignDoi.pattern">The DOI {$pubId} cannot be assigned because it contains an unresolved pattern.</message><message key="plugins.pubIds.doi.editor.assignDoi.assigned">The DOI {$pubId} has been assigned.</message>
<message key="plugins.importexport.pubIds.displayName">Public Identifiers XML Plugin</message><message key="plugins.importexport.pubIds.description">Import and export public identifiers</message><message key="plugins.importexport.pubIds.cliUsage">Usage: {$scriptName} {$pluginName} [command] ...
Commands:
	import [xmlFileName] [journal_path] [user_name]
	export [xmlFileName] [journal_path] issues [issueId1] [issueId2] ...
	export [xmlFileName] [journal_path] issue [issueId]
</message><message key="plugins.importexport.pubIds.export">Export public identifiers</message><message key="plugins.importexport.pubIds.export.forIssues">Export public identifiers</message><message key="plugins.importexport.pubIds.export.selectIssue">Select Issue</message><message key="plugins.importexport.pubIds.export.selectIssue.description">Please select issues, for whose objects you whish to export the public identifiers.</message><message key="plugins.importexport.pubIds.import">Import public identifiers</message><message key="plugins.importexport.pubIds.import.description">This plugin supports the import of the public identifiers based on the pubIds.dtd Document Type Definition.</message><message key="plugins.importexport.pubIds.import.results">Import Results</message><message key="plugins.importexport.pubIds.import.errors">Import Errors</message><message key="plugins.importexport.pubIds.import.errors.description">One or more errors occurred during import. Please check to ensure that the format of the import file correctly matches the specification. Specific details of the import errors are listed below.</message><message key="plugins.importexport.pubIds.import.success">Import Success</message><message key="plugins.importexport.pubIds.import.success.description">Successfully-imported public identifiers are listed below.</message><!-- errors -->
<message key="plugins.importexport.pubIds.cliError">ERROR:</message><message key="plugins.importexport.pubIds.cliError.unknownJournal">The specified journal path, "{$journalPath}", does not exist.</message><message key="plugins.importexport.pubIds.cliError.unknownUser">The specified user, "{$userName}", does not exist.</message><message key="plugins.importexport.pubIds.cliError.issueNotFound">No issue matched the specified issue ID "{$issueId}".</message><message key="plugins.importexport.pubIds.cliError.couldNotWrite">Could not write to the file "{$fileName}".</message><message key="plugins.importexport.pubIds.import.error.uploadFailed">The upload failed; please ensure that uploads are allowed on your server and that the file is not too big for your PHP and web server configuration.</message><message key="plugins.importexport.pubIds.import.error.unsupportedRoot">This plugin does not support the supplied root node "{$rootName}". Please ensure that the file is correctly formed and try again.</message><message key="plugins.importexport.pubIds.import.error.unknownObjectType">An unknown object type "{$pubObjectType}" was specified in the "pubObjectType" attribute of the element with the value "{$pubId}".</message><message key="plugins.importexport.pubIds.import.error.unknownObject">The object "{$pubObjectType}" with ID = {$pubObjectId} specified in the element with the value "{$pubId}" deos not exist for this journal.</message><message key="plugins.importexport.pubIds.import.error.pubIdExists">Public identifier of the type "{$pubIdType}" for the object {$pubObjectType} with ID = {$pubObjectId} already exists.</message><message key="plugins.importexport.pubIds.import.error.duplicatePubId">The public identifier "{$pubId}" is already in use by another object.</message><message key="plugins.importexport.pubIds.import.error.unknownPubId">Your import file contains a public identifier type "{$pubIdType}" that no pubId plugin can handle. Please install and/or activate the corresponding pubId plugin before trying to import this dataset.</message>
<message key="plugins.generic.htmlArticleGalley.displayName">HTML Article Galley</message>
<message key="plugins.generic.htmlArticleGalley.description">Este plugin provee soporte para HTML Article Galleys</message>



	<!-- -->
	<message key="user.login.rememberUsernameAndPassword">Recordar usuario y contraseña</message>
	<message key="manager.setup.layout.sidebar">Gestionar barra lateral</message>
	<message key="plugins.importexport.pubIds.displayName">Módulo XML de identificadores públicos</message>
	<message key="plugins.importexport.pubIds.description">Importar y exportar identificadores públicos</message>
	<message key="plugins.themes.nawi.name">Tema Ñawi</message>
	<message key="plugins.themes.nawi.description">Tema para la revista Ñawi.</message>
  <message key="common.downloadPdf">Descargar PDF.</message>
  <message key="about.onlineSubmissions.newSubmission">Realizar un nuevo envío</message>
  <message key="about.onlineSubmissions.viewSubmissions">Ver tus envíos pendientes</message>
  <message key="about.onlineSubmissions.submissionActions">{$newSubmission} o {$viewSubmissions}.</message>
  <message key="navigation.archives">Volúmenes</message>
  <message key="navigation.current">Convocatoria para publicaciones</message>
  <message key="manager.setup.imgCarousel1">Configurar imagen 1</message>
  <message key="manager.setup.imgCarousel1Description">Puedes cambiar la primera imagen que aparece en la página principal</message>
  <message key="manager.setup.imgCarousel2">Configurar imagen 2</message>
  <message key="manager.setup.imgCarousel2Description">Puedes cambiar la segunda imagen que aparece en la página principal</message>
  <message key="manager.setup.imgCarousel3">Configurar imagen 3</message>
  <message key="manager.setup.imgCarousel3Description">Puedes cambiar la tercera imagen que aparece en la página principal</message>
</locale>
